Python Code:
print("hello world")
Assembly code:
  0           0 RESUME                   0

  1           2 PUSH_NULL
              4 LOAD_NAME                0 (print)
              6 LOAD_CONST               0 ('hello world')
              8 PRECALL                  1
             12 CALL                     1
             22 POP_TOP
             24 LOAD_CONST               1 (None)
             26 RETURN_VALUE


Python Code:
print("hello world")
Assembly code:
  0           0 RESUME                   0

  1           2 PUSH_NULL
              4 LOAD_NAME                0 (print)
              6 LOAD_CONST               0 ('hello world')
              8 PRECALL                  1
             12 CALL                     1
             22 POP_TOP
             24 LOAD_CONST               1 (None)
             26 RETURN_VALUE


